evofr/__init__.py
evofr/cli.py
evofr/commands/prepare_data.py
evofr/commands/registries.py
evofr/commands/run_model.py
evofr/data/__init__.py
evofr/data/case_counts.py
evofr/data/case_frequencies.py
evofr/data/data_helpers.py
evofr/data/data_spec.py
evofr/data/hier_cases.py
evofr/data/hier_frequencies.py
evofr/data/temporal_aggregation.py
evofr/data/variant_frequencies.py
evofr/infer/BJBackendsScrap.py
evofr/infer/InferBlackJax.py
evofr/infer/InferMCMC.py
evofr/infer/InferSVI.py
evofr/infer/MCMC_handler.py
evofr/infer/SVI_handler.py
evofr/infer/SamplePrior.py
evofr/infer/__init__.py
evofr/infer/backends.py
evofr/models/__init__.py
evofr/models/latent_immunity_relative_fitness.py
evofr/models/migration_from_distances.py
evofr/models/mlr_drift.py
evofr/models/mlr_hierarchical.py
evofr/models/mlr_hierarchical_gp.py
evofr/models/mlr_hierarchical_time_varying.py
evofr/models/mlr_innovation.py
evofr/models/mlr_nowcast.py
evofr/models/mlr_sde.py
evofr/models/mlr_spline.py
evofr/models/model_spec.py
evofr/models/multinomial_logistic_regression.py
evofr/models/mutational_fitness_mlr.py
evofr/models/piantham_model.py
evofr/models/relative_fitness_hsgp.py
evofr/models/renewal_model/LAS.py
evofr/models/renewal_model/__init__.py
evofr/models/renewal_model/basis_functions/__init__.py
evofr/models/renewal_model/basis_functions/basis_fns.py
evofr/models/renewal_model/basis_functions/hilbert_space_gaussian_process.py
evofr/models/renewal_model/basis_functions/splines.py
evofr/models/renewal_model/model_factories.py
evofr/models/renewal_model/model_functions.py
evofr/models/renewal_model/model_helpers.py
evofr/models/renewal_model/model_options.py
evofr/models/renewal_model/renewal_model.py
evofr/models/renewal_model/renewal_regression.py
evofr/models/renewal_model/renewal_single_variant.py
evofr/models/renewal_model/spline_incidence.py
evofr/models/selective_pressure.py
evofr/plotting/__init__.py
evofr/plotting/plot_functions.py
evofr/plotting/plotting_classes.py
evofr-0.1.27.dist-info/LICENSE.txt
evofr-0.1.27.dist-info/METADATA
evofr-0.1.27.dist-info/WHEEL
evofr-0.1.27.dist-info/entry_points.txt
evofr-0.1.27.dist-info/RECORD
