Metadata-Version: 2.1
Name: evofr
Version: 0.1.27
Summary: Tools for evolutionary forecasting.
License: AGPL-3.0
Author: marlinfiggins
Author-email: marlinfiggins@gmail.com
Requires-Python: >=3.9,<4.0
Classifier: License :: OSI Approved :: GNU Affero General Public License v3
Classifier: Programming Language :: Python :: 3
Classifier: Programming Language :: Python :: 3.9
Classifier: Programming Language :: Python :: 3.10
Classifier: Programming Language :: Python :: 3.11
Classifier: Programming Language :: Python :: 3.12
Requires-Dist: blackjax (>=0.9.6,<0.10.0)
Requires-Dist: jax (>=0.4.14,<0.5.0)
Requires-Dist: jaxlib (>=0.4.1,<0.5.0)
Requires-Dist: matplotlib (>=3.9,<4.0)
Requires-Dist: numpy (>=1.22.4,<2.0.0)
Requires-Dist: numpyro (>=0.13.2,<0.14.0)
Requires-Dist: pandas (>=1.4.2,<2.0.0)
Requires-Dist: seaborn (>=0.13.2,<0.14.0)
